nionswift_kernel_provisioner/__init__.py
nionswift_kernel_provisioner/kernel_provisioner.py
nionswift_kernel_provisioner/resources/nion_swift_kernel/kernel.json
nionswift_ipython_provisioner-0.1.1.dist-info/METADATA
nionswift_ipython_provisioner-0.1.1.dist-info/WHEEL
nionswift_ipython_provisioner-0.1.1.dist-info/entry_points.txt
nionswift_ipython_provisioner-0.1.1.dist-info/top_level.txt
nionswift_ipython_provisioner-0.1.1.dist-info/RECORD
