Metadata-Version: 2.4
Name: nionswift-ipython-provisioner
Version: 0.1.1
Summary: An ipython kernel provisioner that connects to the Nion Swift ipython kernel.
Author-email: Nion Software <swift@nion.com>
License-Expression: Apache-2.0
Project-URL: Homepage, https://github.com/nion-software/nionswift-ipython-provisioner
Classifier: Development Status :: 4 - Beta
Classifier: Programming Language :: Python :: 3.12
Classifier: Programming Language :: Python :: 3.13
Requires-Python: >=3.12
Requires-Dist: ipykernel
Requires-Dist: tornado
Requires-Dist: jupyter_client>=7.0
Requires-Dist: jupyter_core
Requires-Dist: traitlets
